Metadata-Version: 2.1
Name: flake8-airflow
Version: 0.1.2
Summary: Flake8 extension for Apache Airflow static analysis rules.
Home-page: https://github.com/bradleybonitatibus/flake8-airflow
Author: Bradley Bonitatibus
Author-email: bradleybonitatibus@gmail.com
Keywords: airflow,flake8,static-analysis
Classifier: Programming Language :: Python :: 3
Classifier: Programming Language :: Python :: 3 :: Only
Requires-Python: ~=3.9
License-File: LICENSE
Requires-Dist: flake8 (>=5.0)
